Infineon_DPS310.py
Infineon_DPS310-1.0.0.dist-info/METADATA
Infineon_DPS310-1.0.0.dist-info/WHEEL
Infineon_DPS310-1.0.0.dist-info/top_level.txt
Infineon_DPS310-1.0.0.dist-info/RECORD
